{
    "AWSTemplateFormatVersion": "2010-09-09",
    "Metadata": {
        "AWS::CloudFormation::Designer": {
            "6ed7c6b5-44f5-4720-a132-8998f1013958": {
                "size": {
                    "width": 60,
                    "height": 60
                },
                "position": {
                    "x": 212,
                    "y": 139
                },
                "z": 0
            }
        }
    },
    "Resources": {
        "EC2I3T5BG": {
            "Ec2": {
            "Type": "AWS::EC2::Instance",

            "Properties": {
                "AvailabilityZone": "us-east-1a",
                "InstanceType": "t2.micro",
                "KeyName": "secret-key",
                "ImageId": "ami-04505e74c0741db8d"

            },
            "Metadata": {
                "AWS::CloudFormation::Designer": {
                    "id": "6ed7c6b5-44f5-4720-a132-8998f1013958"
                }
            }
        }
    }
}
